dgbpy/__init__.py
dgbpy/bokehserver.py
dgbpy/deeplearning_apply-client.py
dgbpy/deeplearning_apply-server.py
dgbpy/deeplearning_apply_clientlib.py
dgbpy/deeplearning_apply_serverlib.py
dgbpy/dgbkeras.py
dgbpy/dgbscikit.py
dgbpy/hdf5.py
dgbpy/keras_classes.py
dgbpy/keras_fix.py
dgbpy/keystr.py
dgbpy/mlapply.py
dgbpy/mlapplyrun.py
dgbpy/mlio.py
dgbpy/mlmodel_dGB.py
dgbpy/servicemgr.py
dgbpy/sklearn_classes.py
dgbpy/uibokeh.py
dgbpy/uibokeh_well.py
dgbpy/uikeras.py
dgbpy/uisklearn.py
odpy/__init__.py
odpy/browse_hdf5_seis.py
odpy/common.py
odpy/dbman.py
odpy/gpuinfo.py
odpy/hdf5.py
odpy/iopar.py
odpy/oscommand.py
odpy/ranges.py
odpy/test_ioserv.py
odpy/volpreload.py
odpy/wellman.py
dgbpy_dm-0.1.2.dist-info/LICENSE
dgbpy_dm-0.1.2.dist-info/METADATA
dgbpy_dm-0.1.2.dist-info/WHEEL
dgbpy_dm-0.1.2.dist-info/top_level.txt
dgbpy_dm-0.1.2.dist-info/RECORD
