Metadata-Version: 2.1
Name: dgbpy-dm
Version: 0.1.2
Summary: Useful dgb stuff.
Home-page: http://opendtect.com
Author: David Markus
Author-email: david.datascientist@outlook.com
License: UNKNOWN
Platform: UNKNOWN
Classifier: Programming Language :: Python :: 3
Classifier: License :: OSI Approved :: MIT License
Classifier: Operating System :: OS Independent
Requires-Python: >=3.7
Requires-Dist: bokeh (>=2.1.0)
Requires-Dist: psutil (>=5.8.0)
Requires-Dist: h5py (>=3.1.0)
Requires-Dist: joblib (>=1.0.0)
Requires-Dist: sklearn (>=0.0)
Requires-Dist: jedi (>=0.16)
Requires-Dist: tensorflow (==2.1.0)
Requires-Dist: keras
Requires-Dist: humanfriendly (>=9.1)
Requires-Dist: xgboost (>=1.3.3)
Requires-Dist: flake8
Requires-Dist: autopep8
